main.py
unit_core-0.0.0.dist-info/METADATA
unit_core-0.0.0.dist-info/WHEEL
unit_core-0.0.0.dist-info/top_level.txt
unit_core-0.0.0.dist-info/RECORD
