Metadata-Version: 2.1
Name: unit-core
Version: 0.0.0
Summary: WIP
Author-email: Nick Khitrov <khitrov34@gmail.com>
License: MIT
Requires-Python: >=3.9
Requires-Dist: pytest (>=7.2.2)
